cloudstore/__init__.py
cloudstore/abstract_store.py
cloudstore/cloud_store.py
cloudstore/logger.py
cloudstore/stores/aws.py
cloudstore/stores/azre.py
cloudstore/stores/gcp.py
cloudstore/utils.py
cloudstore-0.3.0.dist-info/entry_points.txt
cloudstore-0.3.0.dist-info/LICENSE
cloudstore-0.3.0.dist-info/WHEEL
cloudstore-0.3.0.dist-info/METADATA
cloudstore-0.3.0.dist-info/RECORD
